Workbook

Sheet ReadMe
A1: Voice EC Map: $100K in 90 Days Revenue Model
A3: Purpose: plan and track $100,000 booked revenue in 13 weeks, led by the $10K Midlife Capacity Partnership.
A5: How to use
A6: 1. Change blue cells on Inputs (prices, payment mix, funnel rates, hours). Yellow cells are key assumptions.
A7: 2. Enter the weekly sales plan in the blue rows at the top of Plan_13wk.
A8: 3. Every Friday, enter actuals in the yellow cells on Scoreboard. Variance and status fill in automatically.
A9: 4. Summary shows booked vs cash, the pipeline you need, and whether founder hours are over capacity.
A11: Color legend
A12: Blue text = hardcoded input / scenario lever
A13: Black text = formula
A14: Green text = link to another sheet
A15: Yellow fill = key assumption or a cell you fill in
... A26: This model is a planning tool, not a forecast guarantee.

Sheet Summary
A1: Summary: $100K in 90 Days
A2: Revenue
A3: 90-day booked revenue target | B3: =Inputs!B45 -> 100000
A4: Planned booked revenue (13 weeks) | B4: =Plan_13wk!B14 -> 103250
A5: Gap vs target (negative = short) | B5: =B4-B3 -> 3250
A6: Plan status | B6: =IF(B4>=B3,"Plan meets target","Plan short of target") -> Plan meets target
A7: Planned cash collected (13 weeks) | B7: =Plan_13wk!B22 -> 87200
A8: Partnership installments still due after week 13 | B8: =Plan_13wk!B12-Plan_13wk!B20 -> 16050
A9: Share of booked revenue from the Partnership | B9: =IFERROR(Plan_13wk!B12/Plan_13wk!B14,0) -> 1
A11: Sales volume
A12: Partnership clients enrolled | B12: =Plan_13wk!B5 -> 10
A13: Booked revenue per Partnership client (net) | B13: =IFERROR(Plan_13wk!B12/Plan_13wk!B5,0) -> 10325
A14: Fit calls to hold | B14: =Plan_13wk!B26 -> 40
A15: Applications needed | B15: =Plan_13wk!B28 -> 83.333333
A16: Conversations needed | B16: =Plan_13wk!B29 -> 333.33333
A17: Conversations per week (average) | B17: =B16/13 -> 25.641026
A19: Capacity
A20: Peak weekly founder hours | B20: =Plan_13wk!B36 -> 35.333333
A21: Founder hours available per week | B21: =Inputs!B42 -> 30
A22: Weeks over capacity | B22: =COUNTIF(Plan_13wk!C38:O38,">0") -> 4
A23: Capacity status | B23: =IF(B22>0,"Over capacity: delegate check-in review or cap enrollments","Within capacity") -> Over capacity: delegate check-in review or cap enrollments

Sheet Inputs
A1: Inputs
A2: Blue = input. Yellow = key assumption. Column C explains each value.
A3: Pricing ($)
A4: Partnership price, paid in full | B4: 10000 | C4: User-approved list price.
A5: 2-pay installment | B5: 5250 | C5: 2 payments, 30 days apart = $10,500.
A6: 2-pay number of payments | B6: 2 | C6: Structural: fixed at 2 by the Plan_13wk cash formulas.
A7: 3-pay installment | B7: 3600 | C7: 3 payments, 30 days apart = $10,800.
A8: 3-pay number of payments | B8: 3 | C8: Structural: fixed at 3 by the Plan_13wk cash formulas.
A9: Weeks between installments | B9: 4 | C9: About 30 days.
A10: 30-Day Beta price | B10: 500 | C10: Existing ladder (VOICE_EC_MAP_MARKETING_CAMPAIGN.md).
A11: Clarity Sprint price | B11: 1000 | C11: Existing ladder.
A12: Workshop price (employer/ERG/women's group) | B12: 3000 | C12: Planning assumption; validate with the first 3 buyers.
A13: Partner pilot setup | B13: 1500 | C13: Existing ladder; the per-client fee is not modeled.
A15: Partnership payment mix
A16: Share paying in full | B16: 0.5 | C16: Offer a paid-in-full bonus to push this up.
A17: Share on 2-pay | B17: 0.25
A18: Share on 3-pay | B18: =1-B16-B17 -> 0.25 | C18: Remainder of 100%.
A20: Front-end credits
A21: Share of Partnership clients credited a Beta/Sprint fee | B21: 0 | C21: Set to 0: the plan is $10K 1:1 enrollments only, with no front-end offers.
A22: Average credit per credited client | B22: 500 | C22: Mostly Beta ($500) upgrades.
A24: Sales funnel
A25: Conversation -> application | B25: 0.25 | C25: Planning assumption. Starting from zero audience, expect this to run lower in weeks 1-4; replace it with actuals from the Ten Seats board.
A26: Application -> fit call booked | B26: 0.6 | C26: Planning assumption; some applicants are routed to the Beta.
A27: Fit call show rate | B27: 0.8 | C27: Planning assumption; reminders at 24h and 1h.
A28: Close rate on held fit calls | B28: 0.25 | C28: Planning assumption; replace with actuals after 10 calls.
A30: Delivery and founder hours (per week)
A31: Weekly 1:1 session length (hrs) | B31: 0.75 | C31: 45-minute weekly session in the 90-day Intensive phase.
A32: Prep + notes per session (hrs) | B32: 0.25
A33: Daily check-ins reviewed per client per week | B33: 5 | C33: Weekday accountability check-ins.
A34: Minutes to review and reply per check-in | B34: 4 | C34: Uses the reply templates.
A35: Intensive hours per client per week | B35: =B31+B32+B33*B34/60 -> 1.3333333 | C35: Calculated.
A36: Group accountability hour (total hrs/week) | B36: 1 | C36: One weekly group planning call covering all clients.
A37: Beta delivery hours each | B37: 2.75 | C37: From the existing unit economics.
A38: Sprint delivery hours each | B38: 5 | C38: From the existing unit economics.
A39: Workshop hours each (prep + delivery) | B39: 6 | C39: Planning assumption.
A40: Onboarding hours per new client (Map session + report) | B40: 6 | C40: Falls in the week of close.
A41: Sales & marketing hours per week | B41: 15 | C41: Outreach, content, fit calls.
A42: Founder hours available per week | B42: 30 | C42: Set this to your real non-clinical hours.
A44: Target
A45: 90-day booked revenue target | B45: 100000 | C45: Goal set by the user.

Sheet Plan_13wk
A1: 13-Week Plan: booked revenue, cash, pipeline, and founder hours
A2: Blue rows are the weekly sales plan: $10K 1:1 enrollments only, starting from zero (weeks 1-3 build the list, then 1 enrollment a week). Everything else is calculated.
A3: Week | B3: Total | C3: 1 | D3: 2 | E3: 3 | F3: 4 | G3: 5 | H3: 6 | I3: 7 | J3: 8 | K3: 9 | L3: 10 | M3: 11 | N3: 12 | O3: 13
A4: Sales plan (inputs)
A5: Partnership closes (#) | B5: =SUM(C5:O5) -> 10 | C5: 0 | D5: 0 | E5: 0 | F5: 1 | G5: 1 | H5: 1 | I5: 1 | J5: 1 | K5: 1 | L5: 1 | M5: 1 | N5: 1 | O5: 1
A6: 30-Day Beta sales (#) | B6: =SUM(C6:O6) -> 0 | C6: 0 | D6: 0 | E6: 0 | F6: 0 | G6: 0 | H6: 0 | I6: 0 | J6: 0 | K6: 0 | L6: 0 | M6: 0 | N6: 0 | O6: 0
A7: Clarity Sprint sales (#) | B7: =SUM(C7:O7) -> 0 | C7: 0 | D7: 0 | E7: 0 | F7: 0 | G7: 0 | H7: 0 | I7: 0 | J7: 0 | K7: 0 | L7: 0 | M7: 0 | N7: 0 | O7: 0
A8: Workshops (#) | B8: =SUM(C8:O8) -> 0 | C8: 0 | D8: 0 | E8: 0 | F8: 0 | G8: 0 | H8: 0 | I8: 0 | J8: 0 | K8: 0 | L8: 0 | M8: 0 | N8: 0 | O8: 0
A9: Partner pilots (#) | B9: =SUM(C9:O9) -> 0 | C9: 0 | D9: 0 | E9: 0 | F9: 0 | G9: 0 | H9: 0 | I9: 0 | J9: 0 | K9: 0 | L9: 0 | M9: 0 | N9: 0 | O9: 0
A11: Booked revenue ($)
A12: Partnership booked (net of credits) | B12: =SUM(C12:O12) -> 103250 | C12: =C5*(Inputs!$B$16*Inputs!$B$4+Inputs!$B$17*Inputs!$B$5*Inputs!$B$6+Inputs!$B$18*Inputs!$B$7*Inputs!$B$8)-C5*Inputs!$B$21*Inputs!$B$22 -> 0 | D12: =D5*(Inputs!$B$16*Inputs!$B$4+Inputs!$B$17*Inputs!$B$5*Inputs!$B$6+Inputs!$B$18*Inputs!$B$7*Inputs!$B$8)-D5*Inputs!$B$21*Inputs!$B$22 -> 0 | E12: =E5*(Inputs!$B$16*Inputs!$B$4+Inputs!$B$17*Inputs!$B$5*Inputs!$B$6+Inputs!$B$18*Inputs!$B$7*Inputs!$B$8)-E5*Inputs!$B$21*Inputs!$B$22 -> 0 | F12: =F5*(Inputs!$B$16*Inputs!$B$4+Inputs!$B$17*Inputs!$B$5*Inputs!$B$6+Inputs!$B$18*Inputs!$B$7*Inputs!$B$8)-F5*Inputs!$B$21*Inputs!$B$22 -> 10325 | G12: =G5*(Inputs!$B$16*Inputs!$B$4+Inputs!$B$17*Inputs!$B$5*Inputs!$B$6+Inputs!$B$18*Inputs!$B$7*Inputs!$B$8)-G5*Inputs!$B$21*Inputs!$B$22 -> 10325 | H12: =H5*(Inputs!$B$16*Inputs!$B$4+Inputs!$B$17*Inputs!$B$5*Inputs!$B$6+Inputs!$B$18*Inputs!$B$7*Inputs!$B$8)-H5*Inputs!$B$21*Inputs!$B$22 -> 10325 | I12: =I5*(Inputs!$B$16*Inputs!$B$4+Inputs!$B$17*Inputs!$B$5*Inputs!$B$6+Inputs!$B$18*Inputs!$B$7*Inputs!$B$8)-I5*Inputs!$B$21*Inputs!$B$22 -> 10325 | J12: =J5*(Inputs!$B$16*Inputs!$B$4+Inputs!$B$17*Inputs!$B$5*Inputs!$B$6+Inputs!$B$18*Inputs!$B$7*Inputs!$B$8)-J5*Inputs!$B$21*Inputs!$B$22 -> 10325 | ... O12: =O5*(Inputs!$B$16*Inputs!$B$4+Inputs!$B$17*Inputs!$B$5*Inputs!$B$6+Inputs!$B$18*Inputs!$B$7*Inputs!$B$8)-O5*Inputs!$B$21*Inputs!$B$22 -> 10325
A13: Front-end booked (Beta, Sprint, Workshop, Pilot) | B13: =SUM(C13:O13) -> 0 | C13: =C6*Inputs!$B$10+C7*Inputs!$B$11+C8*Inputs!$B$12+C9*Inputs!$B$13 -> 0 | D13: =D6*Inputs!$B$10+D7*Inputs!$B$11+D8*Inputs!$B$12+D9*Inputs!$B$13 -> 0 | E13: =E6*Inputs!$B$10+E7*Inputs!$B$11+E8*Inputs!$B$12+E9*Inputs!$B$13 -> 0 | F13: =F6*Inputs!$B$10+F7*Inputs!$B$11+F8*Inputs!$B$12+F9*Inputs!$B$13 -> 0 | G13: =G6*Inputs!$B$10+G7*Inputs!$B$11+G8*Inputs!$B$12+G9*Inputs!$B$13 -> 0 | H13: =H6*Inputs!$B$10+H7*Inputs!$B$11+H8*Inputs!$B$12+H9*Inputs!$B$13 -> 0 | I13: =I6*Inputs!$B$10+I7*Inputs!$B$11+I8*Inputs!$B$12+I9*Inputs!$B$13 -> 0 | J13: =J6*Inputs!$B$10+J7*Inputs!$B$11+J8*Inputs!$B$12+J9*Inputs!$B$13 -> 0 | ... O13: =O6*Inputs!$B$10+O7*Inputs!$B$11+O8*Inputs!$B$12+O9*Inputs!$B$13 -> 0
A14: Total booked | B14: =SUM(C14:O14) -> 103250 | C14: =C12+C13 -> 0 | D14: =D12+D13 -> 0 | E14: =E12+E13 -> 0 | F14: =F12+F13 -> 10325 | G14: =G12+G13 -> 10325 | H14: =H12+H13 -> 10325 | I14: =I12+I13 -> 10325 | J14: =J12+J13 -> 10325 | ... O14: =O12+O13 -> 10325
A15: Cumulative booked | B15: =O15 -> 103250 | C15: =SUM($C$14:C14) -> 0 | D15: =SUM($C$14:D14) -> 0 | E15: =SUM($C$14:E14) -> 0 | F15: =SUM($C$14:F14) -> 10325 | G15: =SUM($C$14:G14) -> 20650 | H15: =SUM($C$14:H14) -> 30975 | I15: =SUM($C$14:I14) -> 41300 | J15: =SUM($C$14:J14) -> 51625 | ... O15: =SUM($C$14:O14) -> 103250
A17: Cash collected ($)
A18: Partnership closes 1 installment ago (#) | C18: =IF(C$3<=Inputs!$B$9,0,INDEX($C$5:$O$5,C$3-Inputs!$B$9)) -> 0 | D18: =IF(D$3<=Inputs!$B$9,0,INDEX($C$5:$O$5,D$3-Inputs!$B$9)) -> 0 | E18: =IF(E$3<=Inputs!$B$9,0,INDEX($C$5:$O$5,E$3-Inputs!$B$9)) -> 0 | F18: =IF(F$3<=Inputs!$B$9,0,INDEX($C$5:$O$5,F$3-Inputs!$B$9)) -> 0 | G18: =IF(G$3<=Inputs!$B$9,0,INDEX($C$5:$O$5,G$3-Inputs!$B$9)) -> 0 | H18: =IF(H$3<=Inputs!$B$9,0,INDEX($C$5:$O$5,H$3-Inputs!$B$9)) -> 0 | I18: =IF(I$3<=Inputs!$B$9,0,INDEX($C$5:$O$5,I$3-Inputs!$B$9)) -> 0 | J18: =IF(J$3<=Inputs!$B$9,0,INDEX($C$5:$O$5,J$3-Inputs!$B$9)) -> 1 | ... O18: =IF(O$3<=Inputs!$B$9,0,INDEX($C$5:$O$5,O$3-Inputs!$B$9)) -> 1
A19: Partnership closes 2 installments ago (#) | C19: =IF(C$3<=2*Inputs!$B$9,0,INDEX($C$5:$O$5,C$3-2*Inputs!$B$9)) -> 0 | D19: =IF(D$3<=2*Inputs!$B$9,0,INDEX($C$5:$O$5,D$3-2*Inputs!$B$9)) -> 0 | E19: =IF(E$3<=2*Inputs!$B$9,0,INDEX($C$5:$O$5,E$3-2*Inputs!$B$9)) -> 0 | F19: =IF(F$3<=2*Inputs!$B$9,0,INDEX($C$5:$O$5,F$3-2*Inputs!$B$9)) -> 0 | G19: =IF(G$3<=2*Inputs!$B$9,0,INDEX($C$5:$O$5,G$3-2*Inputs!$B$9)) -> 0 | H19: =IF(H$3<=2*Inputs!$B$9,0,INDEX($C$5:$O$5,H$3-2*Inputs!$B$9)) -> 0 | I19: =IF(I$3<=2*Inputs!$B$9,0,INDEX($C$5:$O$5,I$3-2*Inputs!$B$9)) -> 0 | J19: =IF(J$3<=2*Inputs!$B$9,0,INDEX($C$5:$O$5,J$3-2*Inputs!$B$9)) -> 0 | ... O19: =IF(O$3<=2*Inputs!$B$9,0,INDEX($C$5:$O$5,O$3-2*Inputs!$B$9)) -> 1
A20: Partnership cash | B20: =SUM(C20:O20) -> 87200 | C20: =C5*Inputs!$B$16*Inputs!$B$4+Inputs!$B$17*Inputs!$B$5*(C5+C18)+Inputs!$B$18*Inputs!$B$7*(C5+C18+C19)-C5*Inputs!$B$21*Inputs!$B$22 -> 0 | D20: =D5*Inputs!$B$16*Inputs!$B$4+Inputs!$B$17*Inputs!$B$5*(D5+D18)+Inputs!$B$18*Inputs!$B$7*(D5+D18+D19)-D5*Inputs!$B$21*Inputs!$B$22 -> 0 | E20: =E5*Inputs!$B$16*Inputs!$B$4+Inputs!$B$17*Inputs!$B$5*(E5+E18)+Inputs!$B$18*Inputs!$B$7*(E5+E18+E19)-E5*Inputs!$B$21*Inputs!$B$22 -> 0 | F20: =F5*Inputs!$B$16*Inputs!$B$4+Inputs!$B$17*Inputs!$B$5*(F5+F18)+Inputs!$B$18*Inputs!$B$7*(F5+F18+F19)-F5*Inputs!$B$21*Inputs!$B$22 -> 7212.5 | G20: =G5*Inputs!$B$16*Inputs!$B$4+Inputs!$B$17*Inputs!$B$5*(G5+G18)+Inputs!$B$18*Inputs!$B$7*(G5+G18+G19)-G5*Inputs!$B$21*Inputs!$B$22 -> 7212.5 | H20: =H5*Inputs!$B$16*Inputs!$B$4+Inputs!$B$17*Inputs!$B$5*(H5+H18)+Inputs!$B$18*Inputs!$B$7*(H5+H18+H19)-H5*Inputs!$B$21*Inputs!$B$22 -> 7212.5 | I20: =I5*Inputs!$B$16*Inputs!$B$4+Inputs!$B$17*Inputs!$B$5*(I5+I18)+Inputs!$B$18*Inputs!$B$7*(I5+I18+I19)-I5*Inputs!$B$21*Inputs!$B$22 -> 7212.5 | J20: =J5*Inputs!$B$16*Inputs!$B$4+Inputs!$B$17*Inputs!$B$5*(J5+J18)+Inputs!$B$18*Inputs!$B$7*(J5+J18+J19)-J5*Inputs!$B$21*Inputs!$B$22 -> 9425 | ... O20: =O5*Inputs!$B$16*Inputs!$B$4+Inputs!$B$17*Inputs!$B$5*(O5+O18)+Inputs!$B$18*Inputs!$B$7*(O5+O18+O19)-O5*Inputs!$B$21*Inputs!$B$22 -> 10325
A21: Front-end cash (paid upfront) | B21: =SUM(C21:O21) -> 0 | C21: =C13 -> 0 | D21: =D13 -> 0 | E21: =E13 -> 0 | F21: =F13 -> 0 | G21: =G13 -> 0 | H21: =H13 -> 0 | I21: =I13 -> 0 | J21: =J13 -> 0 | ... O21: =O13 -> 0
A22: Total cash | B22: =SUM(C22:O22) -> 87200 | C22: =C20+C21 -> 0 | D22: =D20+D21 -> 0 | E22: =E20+E21 -> 0 | F22: =F20+F21 -> 7212.5 | G22: =G20+G21 -> 7212.5 | H22: =H20+H21 -> 7212.5 | I22: =I20+I21 -> 7212.5 | J22: =J20+J21 -> 9425 | ... O22: =O20+O21 -> 10325
A23: Cumulative cash | B23: =O23 -> 87200 | C23: =SUM($C$22:C22) -> 0 | D23: =SUM($C$22:D22) -> 0 | E23: =SUM($C$22:E22) -> 0 | F23: =SUM($C$22:F22) -> 7212.5 | G23: =SUM($C$22:G22) -> 14425 | H23: =SUM($C$22:H22) -> 21637.5 | I23: =SUM($C$22:I22) -> 28850 | J23: =SUM($C$22:J22) -> 38275 | ... O23: =SUM($C$22:O22) -> 87200
A25: Pipeline needed to hit the Partnership plan (work these 1-2 weeks ahead)
A26: Fit calls held | B26: =SUM(C26:O26) -> 40 | C26: =IFERROR(C5/Inputs!$B$28,0) -> 0 | D26: =IFERROR(D5/Inputs!$B$28,0) -> 0 | E26: =IFERROR(E5/Inputs!$B$28,0) -> 0 | F26: =IFERROR(F5/Inputs!$B$28,0) -> 4 | G26: =IFERROR(G5/Inputs!$B$28,0) -> 4 | H26: =IFERROR(H5/Inputs!$B$28,0) -> 4 | I26: =IFERROR(I5/Inputs!$B$28,0) -> 4 | J26: =IFERROR(J5/Inputs!$B$28,0) -> 4 | ... O26: =IFERROR(O5/Inputs!$B$28,0) -> 4
A27: Fit calls booked | B27: =SUM(C27:O27) -> 50 | C27: =IFERROR(C26/Inputs!$B$27,0) -> 0 | D27: =IFERROR(D26/Inputs!$B$27,0) -> 0 | E27: =IFERROR(E26/Inputs!$B$27,0) -> 0 | F27: =IFERROR(F26/Inputs!$B$27,0) -> 5 | G27: =IFERROR(G26/Inputs!$B$27,0) -> 5 | H27: =IFERROR(H26/Inputs!$B$27,0) -> 5 | I27: =IFERROR(I26/Inputs!$B$27,0) -> 5 | J27: =IFERROR(J26/Inputs!$B$27,0) -> 5 | ... O27: =IFERROR(O26/Inputs!$B$27,0) -> 5
A28: Applications | B28: =SUM(C28:O28) -> 83.333333 | C28: =IFERROR(C27/Inputs!$B$26,0) -> 0 | D28: =IFERROR(D27/Inputs!$B$26,0) -> 0 | E28: =IFERROR(E27/Inputs!$B$26,0) -> 0 | F28: =IFERROR(F27/Inputs!$B$26,0) -> 8.3333333 | G28: =IFERROR(G27/Inputs!$B$26,0) -> 8.3333333 | H28: =IFERROR(H27/Inputs!$B$26,0) -> 8.3333333 | I28: =IFERROR(I27/Inputs!$B$26,0) -> 8.3333333 | J28: =IFERROR(J27/Inputs!$B$26,0) -> 8.3333333 | ... O28: =IFERROR(O27/Inputs!$B$26,0) -> 8.3333333
A29: Conversations | B29: =SUM(C29:O29) -> 333.33333 | C29: =IFERROR(C28/Inputs!$B$25,0) -> 0 | D29: =IFERROR(D28/Inputs!$B$25,0) -> 0 | E29: =IFERROR(E28/Inputs!$B$25,0) -> 0 | F29: =IFERROR(F28/Inputs!$B$25,0) -> 33.333333 | G29: =IFERROR(G28/Inputs!$B$25,0) -> 33.333333 | H29: =IFERROR(H28/Inputs!$B$25,0) -> 33.333333 | I29: =IFERROR(I28/Inputs!$B$25,0) -> 33.333333 | J29: =IFERROR(J28/Inputs!$B$25,0) -> 33.333333 | ... O29: =IFERROR(O28/Inputs!$B$25,0) -> 33.333333
A31: Founder hours per week (column B = peak week)
A32: Active Partnership clients (#) | B32: =O32 -> 10 | C32: =SUM($C$5:C5) -> 0 | D32: =SUM($C$5:D5) -> 0 | E32: =SUM($C$5:E5) -> 0 | F32: =SUM($C$5:F5) -> 1 | G32: =SUM($C$5:G5) -> 2 | H32: =SUM($C$5:H5) -> 3 | I32: =SUM($C$5:I5) -> 4 | J32: =SUM($C$5:J5) -> 5 | ... O32: =SUM($C$5:O5) -> 10
A33: Partnership delivery hrs | B33: =MAX(C33:O33) -> 20.333333 | C33: =C32*Inputs!$B$35+IF(C32>0,Inputs!$B$36,0)+C5*Inputs!$B$40 -> 0 | D33: =D32*Inputs!$B$35+IF(D32>0,Inputs!$B$36,0)+D5*Inputs!$B$40 -> 0 | E33: =E32*Inputs!$B$35+IF(E32>0,Inputs!$B$36,0)+E5*Inputs!$B$40 -> 0 | F33: =F32*Inputs!$B$35+IF(F32>0,Inputs!$B$36,0)+F5*Inputs!$B$40 -> 8.3333333 | G33: =G32*Inputs!$B$35+IF(G32>0,Inputs!$B$36,0)+G5*Inputs!$B$40 -> 9.6666667 | H33: =H32*Inputs!$B$35+IF(H32>0,Inputs!$B$36,0)+H5*Inputs!$B$40 -> 11 | I33: =I32*Inputs!$B$35+IF(I32>0,Inputs!$B$36,0)+I5*Inputs!$B$40 -> 12.333333 | J33: =J32*Inputs!$B$35+IF(J32>0,Inputs!$B$36,0)+J5*Inputs!$B$40 -> 13.666667 | ... O33: =O32*Inputs!$B$35+IF(O32>0,Inputs!$B$36,0)+O5*Inputs!$B$40 -> 20.333333
A34: Front-end delivery hrs | B34: =MAX(C34:O34) -> 0 | C34: =C6*Inputs!$B$37+C7*Inputs!$B$38+C8*Inputs!$B$39 -> 0 | D34: =D6*Inputs!$B$37+D7*Inputs!$B$38+D8*Inputs!$B$39 -> 0 | E34: =E6*Inputs!$B$37+E7*Inputs!$B$38+E8*Inputs!$B$39 -> 0 | F34: =F6*Inputs!$B$37+F7*Inputs!$B$38+F8*Inputs!$B$39 -> 0 | G34: =G6*Inputs!$B$37+G7*Inputs!$B$38+G8*Inputs!$B$39 -> 0 | H34: =H6*Inputs!$B$37+H7*Inputs!$B$38+H8*Inputs!$B$39 -> 0 | I34: =I6*Inputs!$B$37+I7*Inputs!$B$38+I8*Inputs!$B$39 -> 0 | J34: =J6*Inputs!$B$37+J7*Inputs!$B$38+J8*Inputs!$B$39 -> 0 | ... O34: =O6*Inputs!$B$37+O7*Inputs!$B$38+O8*Inputs!$B$39 -> 0
A35: Sales & marketing hrs | B35: =MAX(C35:O35) -> 15 | C35: =Inputs!$B$41 -> 15 | D35: =Inputs!$B$41 -> 15 | E35: =Inputs!$B$41 -> 15 | F35: =Inputs!$B$41 -> 15 | G35: =Inputs!$B$41 -> 15 | H35: =Inputs!$B$41 -> 15 | I35: =Inputs!$B$41 -> 15 | J35: =Inputs!$B$41 -> 15 | ... O35: =Inputs!$B$41 -> 15
A36: Total founder hrs | B36: =MAX(C36:O36) -> 35.333333 | C36: =C33+C34+C35 -> 15 | D36: =D33+D34+D35 -> 15 | E36: =E33+E34+E35 -> 15 | F36: =F33+F34+F35 -> 23.333333 | G36: =G33+G34+G35 -> 24.666667 | H36: =H33+H34+H35 -> 26 | I36: =I33+I34+I35 -> 27.333333 | J36: =J33+J34+J35 -> 28.666667 | ... O36: =O33+O34+O35 -> 35.333333
A37: Hours available | B37: =MAX(C37:O37) -> 30 | C37: =Inputs!$B$42 -> 30 | D37: =Inputs!$B$42 -> 30 | E37: =Inputs!$B$42 -> 30 | F37: =Inputs!$B$42 -> 30 | G37: =Inputs!$B$42 -> 30 | H37: =Inputs!$B$42 -> 30 | I37: =Inputs!$B$42 -> 30 | J37: =Inputs!$B$42 -> 30 | ... O37: =Inputs!$B$42 -> 30
A38: Over / (under) capacity | B38: =MAX(C38:O38) -> 5.3333333 | C38: =C36-C37 -> -15 | D38: =D36-D37 -> -15 | E38: =E36-E37 -> -15 | F38: =F36-F37 -> -6.6666667 | G38: =G36-G37 -> -5.3333333 | H38: =H36-H37 -> -4 | I38: =I36-I37 -> -2.6666667 | J38: =J36-J37 -> -1.3333333 | ... O38: =O36-O37 -> 5.3333333
A39: Capacity status | C39: =IF(C38>0,"OVER","OK") -> OK | D39: =IF(D38>0,"OVER","OK") -> OK | E39: =IF(E38>0,"OVER","OK") -> OK | F39: =IF(F38>0,"OVER","OK") -> OK | G39: =IF(G38>0,"OVER","OK") -> OK | H39: =IF(H38>0,"OVER","OK") -> OK | I39: =IF(I38>0,"OVER","OK") -> OK | J39: =IF(J38>0,"OVER","OK") -> OK | ... O39: =IF(O38>0,"OVER","OK") -> OVER

Sheet PayStructure
A1: Pay Structure
A2: Cash timing assumes the first payment at enrollment and later installments every 30 days.
A4: Plan | B4: Installment ($) | C4: # Payments | D4: Total paid ($) | E4: Premium vs PIF ($) | F4: Cash in first 30 days ($) | G4: Cash in first 60 days ($) | H4: Cash in first 90 days ($)
A5: Partnership, paid in full | B5: =Inputs!B4 -> 10000 | C5: 1 | D5: =B5*C5 -> 10000 | E5: =D5-Inputs!$B$4 -> 0 | F5: =B5*MIN(1,C5) -> 10000 | G5: =B5*MIN(2,C5) -> 10000 | H5: =B5*MIN(3,C5) -> 10000
A6: Partnership, 2-pay | B6: =Inputs!B5 -> 5250 | C6: =Inputs!B6 -> 2 | D6: =B6*C6 -> 10500 | E6: =D6-Inputs!$B$4 -> 500 | F6: =B6*MIN(1,C6) -> 5250 | G6: =B6*MIN(2,C6) -> 10500 | H6: =B6*MIN(3,C6) -> 10500
A7: Partnership, 3-pay | B7: =Inputs!B7 -> 3600 | C7: =Inputs!B8 -> 3 | D7: =B7*C7 -> 10800 | E7: =D7-Inputs!$B$4 -> 800 | F7: =B7*MIN(1,C7) -> 3600 | G7: =B7*MIN(2,C7) -> 7200 | H7: =B7*MIN(3,C7) -> 10800
A8: 30-Day Beta | B8: =Inputs!B10 -> 500 | C8: 1 | D8: =B8*C8 -> 500 | E8: =0 -> 0 | F8: =B8*MIN(1,C8) -> 500 | G8: =B8*MIN(2,C8) -> 500 | H8: =B8*MIN(3,C8) -> 500
A9: Clarity Sprint | B9: =Inputs!B11 -> 1000 | C9: 1 | D9: =B9*C9 -> 1000 | E9: =0 -> 0 | F9: =B9*MIN(1,C9) -> 1000 | G9: =B9*MIN(2,C9) -> 1000 | H9: =B9*MIN(3,C9) -> 1000
A10: Workshop | B10: =Inputs!B12 -> 3000 | C10: 1 | D10: =B10*C10 -> 3000 | E10: =0 -> 0 | F10: =B10*MIN(1,C10) -> 3000 | G10: =B10*MIN(2,C10) -> 3000 | H10: =B10*MIN(3,C10) -> 3000
A12: Pay structure rules
A13: Paid-in-full bonus (no discount): a 30-day Integration extension plus a quarterly check-in in the following 6 months. It speeds up cash without lowering the price.
A14: Payment plans cost more ($500 / $800) because they carry collection risk and delay cash.
A15: Beta/Sprint fees are credited toward the Partnership if she enrolls within 30 days.
A16: Refunds: full refund within 7 days of payment if the Map session hasn't happened. After that the fee is non-refundable, and a plan is a commitment to the full amount (see the coaching agreement).
A17: Collect by auto-charge (Stripe subscription schedule or Stripe Invoicing). Never collect installments manually.

Sheet Scoreboard
A1: Weekly Accountability Scoreboard: fill in the yellow cells every Friday
A2: Rule: if actual conversations run below target 2 weeks in a row, fix outreach volume before changing the offer.
A4: Week | B4: Conversations target | C4: Conversations actual | D4: Applications target | E4: Applications actual | F4: Fit calls target | G4: Fit calls actual | H4: Closes target | I4: Closes actual | J4: Cash target ($) | K4: Cash actual ($) | L4: Cash variance ($) | M4: Status
A5: Example | B5: 26 | C5: 22 | D5: 6.5 | E5: 5 | F5: 1.3 | G5: 1 | H5: 0.3 | I5: 0 | J5: 10125 | K5: 0 | L5: (format only: this row is not counted)
A6: 1 | B6: =Plan_13wk!C29 -> 0 | D6: =Plan_13wk!C28 -> 0 | F6: =Plan_13wk!C26 -> 0 | H6: =Plan_13wk!C5 -> 0 | J6: =Plan_13wk!C22 -> 0 | L6: =IF(K6="","",K6-J6) | M6: =IF(C6="","",IF(AND(C6>=B6,K6>=J6),"On track",IF(C6<B6,"Raise outreach","Cash behind")))
A7: 2 | B7: =Plan_13wk!D29 -> 0 | D7: =Plan_13wk!D28 -> 0 | F7: =Plan_13wk!D26 -> 0 | H7: =Plan_13wk!D5 -> 0 | J7: =Plan_13wk!D22 -> 0 | L7: =IF(K7="","",K7-J7) | M7: =IF(C7="","",IF(AND(C7>=B7,K7>=J7),"On track",IF(C7<B7,"Raise outreach","Cash behind")))
A8: 3 | B8: =Plan_13wk!E29 -> 0 | D8: =Plan_13wk!E28 -> 0 | F8: =Plan_13wk!E26 -> 0 | H8: =Plan_13wk!E5 -> 0 | J8: =Plan_13wk!E22 -> 0 | L8: =IF(K8="","",K8-J8) | M8: =IF(C8="","",IF(AND(C8>=B8,K8>=J8),"On track",IF(C8<B8,"Raise outreach","Cash behind")))
A9: 4 | B9: =Plan_13wk!F29 -> 33.333333 | D9: =Plan_13wk!F28 -> 8.3333333 | F9: =Plan_13wk!F26 -> 4 | H9: =Plan_13wk!F5 -> 1 | J9: =Plan_13wk!F22 -> 7212.5 | L9: =IF(K9="","",K9-J9) | M9: =IF(C9="","",IF(AND(C9>=B9,K9>=J9),"On track",IF(C9<B9,"Raise outreach","Cash behind")))
A10: 5 | B10: =Plan_13wk!G29 -> 33.333333 | D10: =Plan_13wk!G28 -> 8.3333333 | F10: =Plan_13wk!G26 -> 4 | H10: =Plan_13wk!G5 -> 1 | J10: =Plan_13wk!G22 -> 7212.5 | L10: =IF(K10="","",K10-J10) | M10: =IF(C10="","",IF(AND(C10>=B10,K10>=J10),"On track",IF(C10<B10,"Raise outreach","Cash behind")))
A11: 6 | B11: =Plan_13wk!H29 -> 33.333333 | D11: =Plan_13wk!H28 -> 8.3333333 | F11: =Plan_13wk!H26 -> 4 | H11: =Plan_13wk!H5 -> 1 | J11: =Plan_13wk!H22 -> 7212.5 | L11: =IF(K11="","",K11-J11) | M11: =IF(C11="","",IF(AND(C11>=B11,K11>=J11),"On track",IF(C11<B11,"Raise outreach","Cash behind")))
A12: 7 | B12: =Plan_13wk!I29 -> 33.333333 | D12: =Plan_13wk!I28 -> 8.3333333 | F12: =Plan_13wk!I26 -> 4 | H12: =Plan_13wk!I5 -> 1 | J12: =Plan_13wk!I22 -> 7212.5 | L12: =IF(K12="","",K12-J12) | M12: =IF(C12="","",IF(AND(C12>=B12,K12>=J12),"On track",IF(C12<B12,"Raise outreach","Cash behind")))
A13: 8 | B13: =Plan_13wk!J29 -> 33.333333 | D13: =Plan_13wk!J28 -> 8.3333333 | F13: =Plan_13wk!J26 -> 4 | H13: =Plan_13wk!J5 -> 1 | J13: =Plan_13wk!J22 -> 9425 | L13: =IF(K13="","",K13-J13) | M13: =IF(C13="","",IF(AND(C13>=B13,K13>=J13),"On track",IF(C13<B13,"Raise outreach","Cash behind")))
A14: 9 | B14: =Plan_13wk!K29 -> 33.333333 | D14: =Plan_13wk!K28 -> 8.3333333 | F14: =Plan_13wk!K26 -> 4 | H14: =Plan_13wk!K5 -> 1 | J14: =Plan_13wk!K22 -> 9425 | L14: =IF(K14="","",K14-J14) | M14: =IF(C14="","",IF(AND(C14>=B14,K14>=J14),"On track",IF(C14<B14,"Raise outreach","Cash behind")))
A15: 10 | B15: =Plan_13wk!L29 -> 33.333333 | D15: =Plan_13wk!L28 -> 8.3333333 | F15: =Plan_13wk!L26 -> 4 | H15: =Plan_13wk!L5 -> 1 | J15: =Plan_13wk!L22 -> 9425 | L15: =IF(K15="","",K15-J15) | M15: =IF(C15="","",IF(AND(C15>=B15,K15>=J15),"On track",IF(C15<B15,"Raise outreach","Cash behind")))
A16: 11 | B16: =Plan_13wk!M29 -> 33.333333 | D16: =Plan_13wk!M28 -> 8.3333333 | F16: =Plan_13wk!M26 -> 4 | H16: =Plan_13wk!M5 -> 1 | J16: =Plan_13wk!M22 -> 9425 | L16: =IF(K16="","",K16-J16) | M16: =IF(C16="","",IF(AND(C16>=B16,K16>=J16),"On track",IF(C16<B16,"Raise outreach","Cash behind")))
A17: 12 | B17: =Plan_13wk!N29 -> 33.333333 | D17: =Plan_13wk!N28 -> 8.3333333 | F17: =Plan_13wk!N26 -> 4 | H17: =Plan_13wk!N5 -> 1 | J17: =Plan_13wk!N22 -> 10325 | L17: =IF(K17="","",K17-J17) | M17: =IF(C17="","",IF(AND(C17>=B17,K17>=J17),"On track",IF(C17<B17,"Raise outreach","Cash behind")))
A18: 13 | B18: =Plan_13wk!O29 -> 33.333333 | D18: =Plan_13wk!O28 -> 8.3333333 | F18: =Plan_13wk!O26 -> 4 | H18: =Plan_13wk!O5 -> 1 | J18: =Plan_13wk!O22 -> 10325 | L18: =IF(K18="","",K18-J18) | M18: =IF(C18="","",IF(AND(C18>=B18,K18>=J18),"On track",IF(C18<B18,"Raise outreach","Cash behind")))
A19: Total | B19: =SUM(B6:B18) -> 333.33333 | C19: =SUM(C6:C18) -> 0 | D19: =SUM(D6:D18) -> 83.333333 | E19: =SUM(E6:E18) -> 0 | F19: =SUM(F6:F18) -> 40 | G19: =SUM(G6:G18) -> 0 | H19: =SUM(H6:H18) -> 10 | I19: =SUM(I6:I18) -> 0 | ... L19: =SUM(L6:L18) -> 0
