Workbook

Sheet ReadMe
A1: Voice EC Map — Phased Business Model: Unit Economics Workbook
A2: Stage 1 (Consulting Wedge) -> Stage 2 (Productized B2C) | Prepared 2026-07-25
A4: What's in this workbook
A5: Stage1_UnitEcon | B5: Per-offer economics for the consulting model you already launched (Paid Beta, Case Clarity Sprint, Provider Pilot). Figures sourced from VOICE_EC_MAP_MARKETING_CAMPAIGN.md.
A6: Stage1_Capacity | B6: How many clients your own hours can carry per month, plus a 12-month revenue ramp that plateaus at that ceiling — the quantitative case for Stage 2.
A7: Stage2_UnitEcon | B7: Unit economics for a self-serve B2C product built on the assessment. New territory — priced against real comps (Inflow, Shimmer) pulled 2026-07-25, everything else flagged as a hypothesis.
A8: Stage2_Scale | B8: What Stage 2 looks like at 100 / 500 / 2,000 / 10,000 new paying customers per month, and how long the dev build takes to pay back.
A9: Transition_Triggers | B9: The specific thresholds that tell you it's time to fund the Stage 2 build. Fill in 'Current Status' as you go.
A10: Summary | B10: Stage 1 vs Stage 2 side by side.
A12: Legend
A13: Sample | B13: Blue text = hardcoded input/assumption — safe to edit
A14: Sample | B14: Black text = formula — recalculates automatically, do not hand-edit
A15: Sample | B15: Green text = link to another tab
A16: Sample | B16: Yellow fill = key assumption worth reviewing before you trust the output
A18: Source documents
A19: • VOICE_EC_MAP_MARKETING_CAMPAIGN.md — offer ladder, pricing, unit economics, revenue targets (2026-05-28)
A20: • VOICE_EC_MAP_WEB_MARKET_RESEARCH.md — TAM/SAM/SOM, competitor landscape, pricing research (2026-05-28)
A21: • DEVELOPER_HANDOFF.md — build phases and scope behind the Stage 2 dev-cost placeholder
A22: • EC_Map_Overview_TINT.pdf — product overview (2026-07)
A23: • Inflow (getinflow.io/faqs) and Shimmer (shimmer.care/cost) — Stage 2 pricing comps, pulled 2026-07-25
A25: Read before you build Stage 2
A26: Stage 1's compliance posture rests on the founder reviewing every report before a client sees it. A true self-serve product removes that gate. Before committing engineering spend to Stage 2, run a regulatory review of the automated-report boundary (FDA SaMD exposure, FTC health-claim risk at scale, scope-of-practice questions for a PMHNP-branded consumer product with no clinician in the loop).

Sheet Stage1_UnitEcon
A1: Stage 1 — Consulting Wedge: Unit Economics
A2: Source: VOICE_EC_MAP_MARKETING_CAMPAIGN.md, 'Unit Economics' section (2026-05-28). Blue = doc-sourced input.
A4: Offer | B4: Price ($) | C4: Hours/Client (Low) | D4: Hours/Client (High) | E4: Hours/Client (Mid) | F4: Effective $/Hour | G4: COGS/Overhead per Client ($) | H4: Gross Margin ($) | I4: Gross Margin (%) | J4: Target CAC Ceiling ($) | K4: Contribution after CAC ($) | L4: Contribution after CAC (%)
A5: Paid Beta | B5: 500 | C5: 2 | D5: 3.5 | E5: =AVERAGE(C5:D5) -> 2.75 | F5: =B5/E5 -> 181.81818 | G5: 45 | H5: =B5-G5 -> 455 | I5: =H5/B5 -> 0.91 | J5: 175 | K5: =H5-J5 -> 280 | L5: =K5/B5 -> 0.56
A6: Case Clarity Sprint | B6: 1000 | C6: 4 | D6: 6 | E6: =AVERAGE(C6:D6) -> 5 | F6: =B6/E6 -> 200 | G6: 75 | H6: =B6-G6 -> 925 | I6: =H6/B6 -> 0.925 | J6: 300 | K6: =H6-J6 -> 625 | L6: =K6/B6 -> 0.625
A7: Provider Pilot (Setup Fee) | B7: 1500 | C7: 8 | D7: 12 | E7: =AVERAGE(C7:D7) -> 10 | F7: =B7/E7 -> 150 | G7: 150 | H7: =B7-G7 -> 1350 | I7: =H7/B7 -> 0.9 | J7: 500 | K7: =H7-J7 -> 850 | L7: =K7/B7 -> 0.56666667
A9: Provider Pilot revenue shown is the $1,500 setup fee only — the source doc references an additional, unquantified 'per-client fee' on top of setup. Treat this row as a floor.
A10: COGS/Overhead per client (col G) is a planning allocation of the $140-$1,000/mo bootstrap-to-focused tool budget (source doc 'Budget Scenarios') across practical monthly capacity. Edit to your actuals.

Sheet Stage1_Capacity
A1: Stage 1 — Capacity & 12-Month Revenue Ramp
A2: Months 1-3 match the campaign doc's stated scenarios exactly. Months 4-12 grow client counts at the rate below, capped at the practical-capacity ceiling.
A4: Founder service-delivery hours available per month | D4: 60 | E4: Hours you personally spend delivering intake review + reports + calls, not marketing/ops time.
A6: Offer | B6: Practical Clients/Month | C6: Price ($, linked) | D6: Hours/Client (Mid, linked) | E6: Hours Required | F6: Revenue ($)
A7: Paid Beta | B7: 10 | C7: =Stage1_UnitEcon!B5 -> 500 | D7: =Stage1_UnitEcon!E5 -> 2.75 | E7: =B7*D7 -> 27.5 | F7: =B7*C7 -> 5000
A8: Case Clarity Sprint | B8: 5 | C8: =Stage1_UnitEcon!B6 -> 1000 | D8: =Stage1_UnitEcon!E6 -> 5 | E8: =B8*D8 -> 25 | F8: =B8*C8 -> 5000
A9: Provider Pilot (Setup Fee) | B9: 1 | C9: =Stage1_UnitEcon!B7 -> 1500 | D9: =Stage1_UnitEcon!E7 -> 10 | E9: =B9*D9 -> 10 | F9: =B9*C9 -> 1500
A10: Total | E10: =SUM(E7:E9) -> 62.5 | F10: =SUM(F7:F9) -> 11500
A11: Hours remaining | E11: =D4-E10 -> -2.5
A12: Capacity utilization | E12: =E10/D4 -> 1.0416667
A14: 12-Month Revenue Ramp
A15: Monthly growth rate (months 4-12), applied to client counts, capped at capacity above: | F15: 0.15
A17: Month | B17: Beta Clients | C17: Sprint Clients | D17: Pilot Clients | E17: Monthly Revenue ($) | F17: Cumulative Revenue ($)
A18: Month 1 | B18: 8 | C18: 0 | D18: 0 | E18: =B18*Stage1_UnitEcon!$B$5+C18*Stage1_UnitEcon!$B$6+D18*Stage1_UnitEcon!$B$7 -> 4000 | F18: =E18 -> 4000
A19: Month 2 | B19: 6 | C19: 2 | D19: 0 | E19: =B19*Stage1_UnitEcon!$B$5+C19*Stage1_UnitEcon!$B$6+D19*Stage1_UnitEcon!$B$7 -> 5000 | F19: =F18+E19 -> 9000
A20: Month 3 | B20: 6 | C20: 2 | D20: 1 | E20: =B20*Stage1_UnitEcon!$B$5+C20*Stage1_UnitEcon!$B$6+D20*Stage1_UnitEcon!$B$7 -> 6500 | F20: =F19+E20 -> 15500
A21: Month 4 | B21: =MIN($B$7,B20*(1+$F$15)) -> 6.9 | C21: =MIN($B$8,C20*(1+$F$15)) -> 2.3 | D21: =MIN($B$9,D20*(1+$F$15)) -> 1 | E21: =B21*Stage1_UnitEcon!$B$5+C21*Stage1_UnitEcon!$B$6+D21*Stage1_UnitEcon!$B$7 -> 7250 | F21: =F20+E21 -> 22750
A22: Month 5 | B22: =MIN($B$7,B21*(1+$F$15)) -> 7.935 | C22: =MIN($B$8,C21*(1+$F$15)) -> 2.645 | D22: =MIN($B$9,D21*(1+$F$15)) -> 1 | E22: =B22*Stage1_UnitEcon!$B$5+C22*Stage1_UnitEcon!$B$6+D22*Stage1_UnitEcon!$B$7 -> 8112.5 | F22: =F21+E22 -> 30862.5
A23: Month 6 | B23: =MIN($B$7,B22*(1+$F$15)) -> 9.12525 | C23: =MIN($B$8,C22*(1+$F$15)) -> 3.04175 | D23: =MIN($B$9,D22*(1+$F$15)) -> 1 | E23: =B23*Stage1_UnitEcon!$B$5+C23*Stage1_UnitEcon!$B$6+D23*Stage1_UnitEcon!$B$7 -> 9104.375 | F23: =F22+E23 -> 39966.875
A24: Month 7 | B24: =MIN($B$7,B23*(1+$F$15)) -> 10 | C24: =MIN($B$8,C23*(1+$F$15)) -> 3.4980125 | D24: =MIN($B$9,D23*(1+$F$15)) -> 1 | E24: =B24*Stage1_UnitEcon!$B$5+C24*Stage1_UnitEcon!$B$6+D24*Stage1_UnitEcon!$B$7 -> 9998.0125 | F24: =F23+E24 -> 49964.887
A25: Month 8 | B25: =MIN($B$7,B24*(1+$F$15)) -> 10 | C25: =MIN($B$8,C24*(1+$F$15)) -> 4.0227144 | D25: =MIN($B$9,D24*(1+$F$15)) -> 1 | E25: =B25*Stage1_UnitEcon!$B$5+C25*Stage1_UnitEcon!$B$6+D25*Stage1_UnitEcon!$B$7 -> 10522.714 | F25: =F24+E25 -> 60487.602
A26: Month 9 | B26: =MIN($B$7,B25*(1+$F$15)) -> 10 | C26: =MIN($B$8,C25*(1+$F$15)) -> 4.6261215 | D26: =MIN($B$9,D25*(1+$F$15)) -> 1 | E26: =B26*Stage1_UnitEcon!$B$5+C26*Stage1_UnitEcon!$B$6+D26*Stage1_UnitEcon!$B$7 -> 11126.122 | F26: =F25+E26 -> 71613.723
A27: Month 10 | B27: =MIN($B$7,B26*(1+$F$15)) -> 10 | C27: =MIN($B$8,C26*(1+$F$15)) -> 5 | D27: =MIN($B$9,D26*(1+$F$15)) -> 1 | E27: =B27*Stage1_UnitEcon!$B$5+C27*Stage1_UnitEcon!$B$6+D27*Stage1_UnitEcon!$B$7 -> 11500 | F27: =F26+E27 -> 83113.723
A28: Month 11 | B28: =MIN($B$7,B27*(1+$F$15)) -> 10 | C28: =MIN($B$8,C27*(1+$F$15)) -> 5 | D28: =MIN($B$9,D27*(1+$F$15)) -> 1 | E28: =B28*Stage1_UnitEcon!$B$5+C28*Stage1_UnitEcon!$B$6+D28*Stage1_UnitEcon!$B$7 -> 11500 | F28: =F27+E28 -> 94613.723
A29: Month 12 | B29: =MIN($B$7,B28*(1+$F$15)) -> 10 | C29: =MIN($B$8,C28*(1+$F$15)) -> 5 | D29: =MIN($B$9,D28*(1+$F$15)) -> 1 | E29: =B29*Stage1_UnitEcon!$B$5+C29*Stage1_UnitEcon!$B$6+D29*Stage1_UnitEcon!$B$7 -> 11500 | F29: =F28+E29 -> 106113.72
A31: Year-1 total | F31: =F29 -> 106113.72
A32: Sanity check vs. source SOM range | D32: =IF(F31>=100000,"Meets aggressive SOM (>$100k, source: web market research doc)",IF(F31>=49300,"Within conservative-to-healthy SOM range ($49,300-$61,000+)","Below conservative SOM ($49,300) — raise growth rate or offer mix")) -> Meets aggressive SOM (>$100k, source: web market research doc)
A34: The ramp plateaus once client counts hit the practical-capacity ceiling (rows 7-9) — that ceiling is the quantitative case for Stage 2.

Sheet Stage2_UnitEcon
A1: Stage 2 — Productized B2C: Unit Economics (Planning Hypothesis)
A2: New territory — not in existing docs. Comps sourced 2026-07-25 (Inflow, Shimmer); everything else is a placeholder to validate.
A4: Assumptions
A5: One-time report price ($) | B5: 99 | C5: Hypothesis, range $79-$149 — no human review, so priced well below Stage 1's $500.
A6: Subscription price ($/month) | B6: 19.99 | C6: Hypothesis, range $14.99-$24.99 — bounded by Inflow $47.99/mo (self-serve app, no clinical spine) and Shimmer ~$260/mo (human coaching).
A7: Variable cost per active user/month ($) — hosting + AI inference + support | B7: 5 | C7: NOT sourced. Placeholder — confirm with vendor quotes once the voice pipeline is scoped.
A8: Payment processing fee (%) | B8: 0.029 | C8: Typical card-processing rate — confirm with processor.
A9: Payment processing fixed fee ($) | B9: 0.3 | C9: Typical card-processing fixed fee — confirm with processor.
A10: Monthly subscription churn (%) | B10: 0.08 | C10: Planning estimate; consumer wellness-app churn often runs 5-12%/mo. Validate.
A11: Blended CAC per new paying customer ($) | B11: 30 | C11: Hypothesis, range $15-$40. Refine per channel once paid tests run.
A13: Metric | B13: One-Time Report | C13: Subscription (per user)
A14: Price ($) | B14: =B5 -> 99 | C14: =B6 -> 19.99
A15: Payment processing fee ($) | B15: =B14*$B$8+$B$9 -> 3.171 | C15: =C14*$B$8+$B$9 -> 0.87971
A16: Variable cost ($) | B16: =$B$7 -> 5 | C16: =$B$7 -> 5
A17: Gross margin ($) | B17: =B14-B15-B16 -> 90.829 | C17: =C14-C15-C16 -> 14.11029
A18: Gross margin (%) | B18: =B17/B14 -> 0.91746465 | C18: =C17/C14 -> 0.70586743
A19: CAC ($) | B19: =$B$11 -> 30 | C19: =$B$11 -> 30
A20: LTV ($) — subscription only | C20: =C17/$B$10 -> 176.37862
A21: LTV : CAC ratio | C21: =C20/C19 -> 5.8792875
A22: Contribution after CAC, per unit ($) — one-time only | B22: =B17-B19 -> 60.829
A23: CAC payback period (months) — subscription only | C23: =IFERROR($B$11/C17,"n/a") -> 2.126108
A25: Bounding comps (sourced 2026-07-25)
A26: • Inflow — self-serve ADHD app, CBT-based daily exercises, no clinical spine, no human review: $47.99/month or $199/year. Source: getinflow.io/faqs
A27: • Shimmer — human 1:1 ADHD coaching, weekly 30-min sessions + extras: $240 every 4 weeks (~$260/month). Source: shimmer.care/cost
A28: • EC Map Stage 2 read: more structured than Inflow (deterministic scoring spine, coach-packet-style report) but with no human review, so it should price below Stage 1's $500 human-reviewed product and below Inflow's pure self-help subscription until the tracking value is proven.

Sheet Stage2_Scale
A1: Stage 2 — Scale Scenarios & Build-Cost Payback
A2: Illustrative only. Flex the two assumptions below; everything underneath recalculates.
A4: Dev build cost estimate ($) — PLACEHOLDER | D4: 50000
A5: Replace with an actual developer quote — see DEVELOPER_HANDOFF.md 'Recommended Developer Path' Phase 1-3 (typed framework, auth, encrypted persistence, coach dashboard, voice pipeline). Plausible range $30k-$100k+ depending on scope.
A6: Share of new paying customers choosing subscription (vs. one-time report) | D6: 0.4
A8: Metric | B8: 100/mo | C8: 500/mo | D8: 2,000/mo | E8: 10,000/mo
A9: New paying customers acquired/month | B9: 100 | C9: 500 | D9: 2000 | E9: 10000
A10: → One-time report buyers | B10: =B9*(1-$D$6) -> 60 | C10: =C9*(1-$D$6) -> 300 | D10: =D9*(1-$D$6) -> 1200 | E10: =E9*(1-$D$6) -> 6000
A11: → New subscribers | B11: =B9*$D$6 -> 40 | C11: =C9*$D$6 -> 200 | D11: =D9*$D$6 -> 800 | E11: =E9*$D$6 -> 4000
A12: Steady-state subscriber base (new subs / churn) | B12: =B11/Stage2_UnitEcon!$B$10 -> 500 | C12: =C11/Stage2_UnitEcon!$B$10 -> 2500 | D12: =D11/Stage2_UnitEcon!$B$10 -> 10000 | E12: =E11/Stage2_UnitEcon!$B$10 -> 50000
A13: Monthly one-time revenue ($) | B13: =B10*Stage2_UnitEcon!$B$5 -> 5940 | C13: =C10*Stage2_UnitEcon!$B$5 -> 29700 | D13: =D10*Stage2_UnitEcon!$B$5 -> 118800 | E13: =E10*Stage2_UnitEcon!$B$5 -> 594000
A14: Monthly subscription revenue ($, steady state) | B14: =B12*Stage2_UnitEcon!$B$6 -> 9995 | C14: =C12*Stage2_UnitEcon!$B$6 -> 49975 | D14: =D12*Stage2_UnitEcon!$B$6 -> 199900 | E14: =E12*Stage2_UnitEcon!$B$6 -> 999500
A15: Total monthly revenue ($) | B15: =B13+B14 -> 15935 | C15: =C13+C14 -> 79675 | D15: =D13+D14 -> 318700 | E15: =E13+E14 -> 1593500
A16: Total monthly variable cost ($) | B16: =(B10+B12)*Stage2_UnitEcon!$B$7+B10*(Stage2_UnitEcon!$B$5*Stage2_UnitEcon!$B$8+Stage2_UnitEcon!$B$9)+B11*(Stage2_UnitEcon!$B$6*Stage2_UnitEcon!$B$8+Stage2_UnitEcon!$B$9) -> 3025.4484 | C16: =(C10+C12)*Stage2_UnitEcon!$B$7+C10*(Stage2_UnitEcon!$B$5*Stage2_UnitEcon!$B$8+Stage2_UnitEcon!$B$9)+C11*(Stage2_UnitEcon!$B$6*Stage2_UnitEcon!$B$8+Stage2_UnitEcon!$B$9) -> 15127.242 | D16: =(D10+D12)*Stage2_UnitEcon!$B$7+D10*(Stage2_UnitEcon!$B$5*Stage2_UnitEcon!$B$8+Stage2_UnitEcon!$B$9)+D11*(Stage2_UnitEcon!$B$6*Stage2_UnitEcon!$B$8+Stage2_UnitEcon!$B$9) -> 60508.968 | E16: =(E10+E12)*Stage2_UnitEcon!$B$7+E10*(Stage2_UnitEcon!$B$5*Stage2_UnitEcon!$B$8+Stage2_UnitEcon!$B$9)+E11*(Stage2_UnitEcon!$B$6*Stage2_UnitEcon!$B$8+Stage2_UnitEcon!$B$9) -> 302544.84
A17: Gross margin ($, before CAC) | B17: =B15-B16 -> 12909.552 | C17: =C15-C16 -> 64547.758 | D17: =D15-D16 -> 258191.03 | E17: =E15-E16 -> 1290955.2
A18: Gross margin (%) | B18: =B17/B15 -> 0.81013816 | C18: =C17/C15 -> 0.81013816 | D18: =D17/D15 -> 0.81013816 | E18: =E17/E15 -> 0.81013816
A19: Monthly CAC spend ($) | B19: =B9*Stage2_UnitEcon!$B$11 -> 3000 | C19: =C9*Stage2_UnitEcon!$B$11 -> 15000 | D19: =D9*Stage2_UnitEcon!$B$11 -> 60000 | E19: =E9*Stage2_UnitEcon!$B$11 -> 300000
A20: Monthly contribution after CAC ($) | B20: =B17-B19 -> 9909.5516 | C20: =C17-C19 -> 49547.758 | D20: =D17-D19 -> 198191.03 | E20: =E17-E19 -> 990955.16
A21: Build-cost payback (months) | B21: =IFERROR($D$4/B20,"n/a") -> 5.045637 | C21: =IFERROR($D$4/C20,"n/a") -> 1.0091274 | D21: =IFERROR($D$4/D20,"n/a") -> 0.25228185 | E21: =IFERROR($D$4/E20,"n/a") -> 0.05045637
A23: Subscriber base assumes steady state (monthly new subscribers = monthly churned subscribers). Real ramp-up will take longer to reach these revenue figures in the early months.

Sheet Transition_Triggers
A1: Transition Triggers — When To Fund Stage 2
A2: Fill in 'Current Status' as real numbers come in. This tab is meant to be revisited, not answered once.
A4: Trigger | B4: Metric | C4: Target | D4: Direction | E4: Current Status (fill in) | F4: Met?
A5: Proof of demand | B5: Cumulative Beta + Sprint + Pilot clients completed | C5: 20 | D5: >= | F5: =IF(E5="","",IF(D5=">=",IF(E5>=C5,"Yes","Not yet"),IF(E5<=C5,"Yes","Not yet")))
A6: Delivery quality | B6: "Next conversation clarity" client rating (source: campaign doc KPI dashboard) | C6: 8 | D6: >= | F6: =IF(E6="","",IF(D6=">=",IF(E6>=C6,"Yes","Not yet"),IF(E6<=C6,"Yes","Not yet")))
A7: Delivery quality | B7: Refund rate | C7: 0.05 | D7: <= | F7: =IF(E7="","",IF(D7=">=",IF(E7>=C7,"Yes","Not yet"),IF(E7<=C7,"Yes","Not yet")))
A8: Capacity ceiling reached | B8: Consecutive months turning away qualified leads at full capacity | C8: 2 | D8: >= | F8: =IF(E8="","",IF(D8=">=",IF(E8>=C8,"Yes","Not yet"),IF(E8<=C8,"Yes","Not yet")))
A9: Organic pull | B9: Share of new leads arriving without founder outreach | C9: 0.25 | D9: >= | F9: =IF(E9="","",IF(D9=">=",IF(E9>=C9,"Yes","Not yet"),IF(E9<=C9,"Yes","Not yet")))
A10: Price/format objection signal | B10: Share of fit-call leads citing "want to try it myself first" or price friction | C10: 0.15 | D10: >= | F10: =IF(E10="","",IF(D10=">=",IF(E10>=C10,"Yes","Not yet"),IF(E10<=C10,"Yes","Not yet")))
A11: Compliance groundwork | B11: Security threat model + regulatory review of the no-human-review boundary complete (1 = yes) | C11: 1 | D11: >= | F11: =IF(E11="","",IF(D11=">=",IF(E11>=C11,"Yes","Not yet"),IF(E11<=C11,"Yes","Not yet")))
A12: Funding secured | B12: Stage 1 profit reserve or outside capital covers the dev build quote (1 = yes) | C12: 1 | D12: >= | F12: =IF(E12="","",IF(D12=">=",IF(E12>=C12,"Yes","Not yet"),IF(E12<=C12,"Yes","Not yet")))
A14: Triggers met | F14: =COUNTIF(F5:F12,"Yes") -> 0
A15: Recommendation | B15: =IF(F14>=6,"Green light — begin Stage 2 scoping",IF(F14>=4,"Directionally ready — close remaining gaps first","Not yet — stay focused on Stage 1 proof")) -> Not yet — stay focused on Stage 1 proof

Sheet Summary
A1: Summary Dashboard — Stage 1 vs Stage 2
A2: Stage 2 shown at the 2,000 new-paying-customers/month scenario (Stage2_Scale col D).
A4: Metric | B4: Stage 1 — Consulting Wedge | C4: Stage 2 — Productized B2C
A5: Monthly revenue (practical ceiling / illustrative) | B5: =Stage1_Capacity!F10 -> 11500 | C5: =Stage2_Scale!D14 -> 199900
A6: Gross margin (%) | B6: =SUMPRODUCT(Stage1_Capacity!B7:B9,Stage1_UnitEcon!H5:H7)/Stage1_Capacity!F10 -> 0.91521739 | C6: =Stage2_Scale!D18 -> 0.81013816
A7: CAC | B7: $175-$500 depending on offer (source: campaign doc) | C7: =Stage2_UnitEcon!B11 -> 30
A8: Founder hours per $1,000 revenue | B8: =Stage1_Capacity!E10/Stage1_Capacity!F10*1000 -> 5.4347826 | C8: ~0 (automated, no founder hours/unit)
A9: Time to first revenue | B9: Immediate — offer is already live | C9: 6-12+ months (build required, see DEVELOPER_HANDOFF Phase 1-3)
A10: Compliance posture | B10: Lower risk — every report human-reviewed before delivery (founder review gate) | C10: Materially different — no human-review gate by default. Run the health-adjacent-regulatory-dossier review before build.
A12: Read together with Transition_Triggers: Stage 1 funds itself and proves the offer today; Stage 2 removes the founder-hours ceiling but needs a real dev quote, a subscription/one-time price test, and a regulatory review of the no-human-review boundary before it's a launch decision rather than a hypothesis.
